pullyou.py
pullyou-1.0.2.dist-info/LICENSE
pullyou-1.0.2.dist-info/METADATA
pullyou-1.0.2.dist-info/WHEEL
pullyou-1.0.2.dist-info/entry_points.txt
pullyou-1.0.2.dist-info/top_level.txt
pullyou-1.0.2.dist-info/RECORD
